ChengxuyuanMianshiJindianDiliubanQuanjieDoocsKaiyuanShequFix1/README.md
ChengxuyuanMianshiJindianDiliubanQuanjieDoocsKaiyuanShequFix1/__init__.py
ChengxuyuanMianshiJindianDiliubanQuanjieDoocsKaiyuanShequFix1/__main__.py
ChengxuyuanMianshiJindianDiliubanQuanjieDoocsKaiyuanShequFix1/file.epub
ChengxuyuanMianshiJindianDiliubanQuanjieDoocsKaiyuanShequFix1/index.html
ChengxuyuanMianshiJindianDiliubanQuanjieDoocsKaiyuanShequFix1/css/__init__.py
ChengxuyuanMianshiJindianDiliubanQuanjieDoocsKaiyuanShequFix1/css/annotations.css
ChengxuyuanMianshiJindianDiliubanQuanjieDoocsKaiyuanShequFix1/css/main.css
ChengxuyuanMianshiJindianDiliubanQuanjieDoocsKaiyuanShequFix1/css/normalize.css
ChengxuyuanMianshiJindianDiliubanQuanjieDoocsKaiyuanShequFix1/css/popup.css
ChengxuyuanMianshiJindianDiliubanQuanjieDoocsKaiyuanShequFix1/font/__init__.py
ChengxuyuanMianshiJindianDiliubanQuanjieDoocsKaiyuanShequFix1/font/fontello.eot
ChengxuyuanMianshiJindianDiliubanQuanjieDoocsKaiyuanShequFix1/font/fontello.svg
ChengxuyuanMianshiJindianDiliubanQuanjieDoocsKaiyuanShequFix1/font/fontello.ttf
ChengxuyuanMianshiJindianDiliubanQuanjieDoocsKaiyuanShequFix1/font/fontello.woff
ChengxuyuanMianshiJindianDiliubanQuanjieDoocsKaiyuanShequFix1/img/__init__.py
ChengxuyuanMianshiJindianDiliubanQuanjieDoocsKaiyuanShequFix1/img/annotator-glyph-sprite.png
ChengxuyuanMianshiJindianDiliubanQuanjieDoocsKaiyuanShequFix1/img/annotator-icon-sprite.png
ChengxuyuanMianshiJindianDiliubanQuanjieDoocsKaiyuanShequFix1/img/apple-touch-icon.png
ChengxuyuanMianshiJindianDiliubanQuanjieDoocsKaiyuanShequFix1/img/cancelfullscreen.png
ChengxuyuanMianshiJindianDiliubanQuanjieDoocsKaiyuanShequFix1/img/close.png
ChengxuyuanMianshiJindianDiliubanQuanjieDoocsKaiyuanShequFix1/img/fullscreen.png
ChengxuyuanMianshiJindianDiliubanQuanjieDoocsKaiyuanShequFix1/img/loader.gif
ChengxuyuanMianshiJindianDiliubanQuanjieDoocsKaiyuanShequFix1/img/menu-icon.png
ChengxuyuanMianshiJindianDiliubanQuanjieDoocsKaiyuanShequFix1/img/save.png
chengxuyuan_mianshi_jindian_diliuban_quanjie_doocs_kaiyuan_shequ_fix1-2025.3.25.0.dist-info/METADATA
chengxuyuan_mianshi_jindian_diliuban_quanjie_doocs_kaiyuan_shequ_fix1-2025.3.25.0.dist-info/WHEEL
chengxuyuan_mianshi_jindian_diliuban_quanjie_doocs_kaiyuan_shequ_fix1-2025.3.25.0.dist-info/entry_points.txt
chengxuyuan_mianshi_jindian_diliuban_quanjie_doocs_kaiyuan_shequ_fix1-2025.3.25.0.dist-info/top_level.txt
chengxuyuan_mianshi_jindian_diliuban_quanjie_doocs_kaiyuan_shequ_fix1-2025.3.25.0.dist-info/RECORD
